Workbook

Sheet Prime Recipient
B3: Project Title: | E3: Southern University Industrial Training and Assessment Center (SU ITAC)
B4: Applicant Name (Prime Recipient): | E4: Southern University and A&M College (Baton Rouge, LA) — UEI H7CJA7NX9WN3
B5: Application track (1 or 2): | E5: 1
B8: Category | C8: Budget Period 1 | D8: Budget Period 2 | E8: Budget Period 3 | F8: Budget Period 4 | G8: Budget Period 5 | H8: TOTAL | I8: Description/Explanation/Details (Please include any additional information necessary to clarify or otherwise enable reviewers to evaluate reasonableness of budget)
B9: Principal Investigator | C9: 30389 | D9: 31300 | E9: 32239 | F9: 33207 | G9: 34203 | H9: =SUM(C9,D9,E9,F9,G9) -> 161338 | I9: Dr. Fareed Dawan, PI & ITAC Director (Tenured Associate Professor, Mechanical Engineering): ~1.5 summer months, Y1 salary $24,000 + 26.62% fringe (9-month faculty summer rate, per Southern's LIFT budget); 3%/yr escalation. [OSP to confirm base salary and rate.]
B10: Technical Staff | C10: 46164 | D10: 47549 | E10: 48975 | F10: 50445 | G10: 51958 | H10: =SUM(C10,D10,E10,F10,G10) -> 245091 | I10: Co-PIs and senior faculty, 3%/yr escalation: Dr. Brian Warren (Co-PI, Associate Director for Energy Assessments; ~1.5 summer months, $20,000) and EE/CEE faculty leads ($8,000) at 26.62% fringe; Dr. Patrick Mensah (Co-PI; 12-month appointment, ~2.5% effort, $8,000) at 33.88% fringe. Dr. Michael Stubblefield (Co-PI) and Deanna Smith (federal contracting and mentor-protégé lead) contribute effort as cost share.
B11: Administrative Staff | C11: 37708 | D11: 38839 | E11: 40004 | F11: 41205 | G11: 42441 | H11: =SUM(C11,D11,E11,F11,G11) -> 200197 | I11: Center Administrator, 0.5 FTE: Deidre H. Street, Executive Director for Outreach and Research Engagement. Y1 $27,500 + 37.12% fringe (staff rate, per Southern's LIFT budget); 3%/yr escalation. Budget, milestone invoicing, cost-share documentation, scheduling, reporting.
B12: Student Employment | C12: 64000 | D12: 96000 | E12: 96000 | F12: 96000 | G12: 96000 | H12: =SUM(C12,D12,E12,F12,G12) -> 448000 | I12: Paid student assessors: 16 in BP1, 24 in BP2–5; ~250 hrs/yr each at $16/hr (≈10 hrs/wk in term plus summer). ~75% undergraduate, 25% graduate. Students beyond 24 counted as trained in the narrative (26–28 in BP3–5) participate through the Industrial Energy Systems and Assessment elective and capstone projects and are not paid.
B13: Equipment and Supplies | C13: 45000 | D13: 12000 | E13: 12000 | F13: 12000 | G13: 12000 | H13: =SUM(C13,D13,E13,F13,G13) -> 93000 | I13: BP1: assessment instrumentation $40,000 (power/power-quality loggers, thermal camera, ultrasonic leak detector, combustion analyzer, airflow, lighting, temperature and current loggers) + supplies, PPE, and software $5,000. BP2–5: calibration and replacement $5,000 + supplies, PPE, and software $7,000.
B14: Travel | C14: 14000 | D14: 24000 | E14: 24000 | F14: 24000 | G14: 24000 | H14: =SUM(C14,D14,E14,F14,G14) -> 110000 | I14: Site visits across north and central Louisiana, the Delta, and southwest Mississippi from Baton Rouge and the Southern University at Shreveport satellite (round trips of up to ~500 miles; ~10 visits in BP1, ~20/yr after; mileage, lodging, per diem) plus 2 DOE ITAC director and peer-learning meetings per year.
B15: Vendors | C15: 0 | D15: 0 | E15: 0 | F15: 0 | G15: 0 | H15: =SUM(C15,D15,E15,F15,G15) -> 0 | I15: None. Strategic Value Plus Solutions is budgeted as a subrecipient (see Subrecipients tab).
B16: Other Costs | C16: 4500 | D16: 7000 | E16: 7000 | F16: 7000 | G16: 7000 | H16: =SUM(C16,D16,E16,F16,G16) -> 32500 | I16: BP1: Certified Energy Manager training and exam for the energy-assessment lead ($2,500); ITAC Industry Day, certificate ceremony, and outreach materials ($2,000). BP2–5: student research and recognition awards ($5,000) and Industry Day, ceremony, and outreach materials ($2,000).
B17: Facilities & Administrative (indirect) | C17: 33239 | D17: 18312 | E17: 14782 | F17: 11143 | G17: 7398 | H17: =SUM(C17,D17,E17,F17,G17) -> 84874 | I17: Institutional facilities & administrative costs retained within the firm-fixed-price amount: balance to $375,000/yr, falling from 9.7% of direct costs in BP1 to 2.0% in BP5 as salaries escalate. [OSP to confirm acceptable; otherwise reduce escalation or other lines.]
C19: =SUM(C9:C18) -> 275000 | D19: =SUM(D9:D18) -> 275000 | E19: =SUM(E9:E18) -> 275000 | F19: =SUM(F9:F18) -> 275000 | G19: =SUM(G9:G18) -> 275000 | H19: =SUM(C19:G19) -> 1375000
B20: Total -- Subrecipients | C20: =+Subrecipients!C11 -> 100000 | D20: =+Subrecipients!D11 -> 100000 | E20: =+Subrecipients!E11 -> 100000 | F20: =+Subrecipients!F11 -> 100000 | G20: =+Subrecipients!G11 -> 100000 | H20: =SUM(C20:G20) -> 500000
B21: TOTAL (Federal Share) | C21: =SUM(C19:C20) -> 375000 | D21: =SUM(D19:D20) -> 375000 | E21: =SUM(E19:E20) -> 375000 | F21: =SUM(F19:F20) -> 375000 | G21: =SUM(G19:G20) -> 375000 | H21: =SUM(C21:G21) -> 1875000
B22: Southern University and A&M College | C22: 73750 | D22: 73750 | E22: 73750 | F22: 73750 | G22: 73750 | H22: =SUM(C22,D22,E22,F22,G22) -> 368750 | I22: In-kind $63,750/yr + cash $10,000/yr: faculty and Co-PI effort not charged to the award, with fringe ($43,750), including academic-year faculty presence on site visits (every BP1 visit and each new team's first visit) and the effort of Dr. Stubblefield and Deanna Smith; use of the Advanced Metal AM Laboratory, XR Jags immersive-training capability, Center space, and departmental labs ($20,000); cash student scholarships and research stipends ($10,000). Documented per 7 CFR 1486.401 in Southern's institutional letter.
B23: Strategic Value Plus Solutions, LLC (V+) | C23: 20000 | D23: 20000 | E23: 20000 | F23: 20000 | G23: 20000 | H23: =SUM(C23,D23,E23,F23,G23) -> 100000 | I23: In-kind: V+ field-engineer and senior-advisor hours not billed to the award.
B24: HUBZone Contractors National Council | C24: 6000 | D24: 6000 | E24: 6000 | F24: 6000 | G24: 6000 | H24: =SUM(C24,D24,E24,F24,G24) -> 30000 | I24: In-kind, $6,000/yr: HUBZone readiness lead. Council participation (8 hrs); two HUBZone readiness workshops for client plants covering eligibility (principal office and 35% employee residency), certification, the SBA HUBZone map, and set-aside, sole-source, and price-preference benefits (14 hrs incl. prep); 22 hrs × $150/hr = $3,300, plus waived registrations for ~9 ITAC clients and students at HUBZone events (~$2,700 fair market value). [Confirm in HCNC letter.]
B25: KDM & Associates | C25: 5000 | D25: 5000 | E25: 5000 | F25: 5000 | G25: 5000 | H25: =SUM(C25,D25,E25,F25,G25) -> 25000 | I25: In-kind, $5,000/yr: federal contracting teaming lead. Council participation (8 hrs); two federal contracting and teaming workshops for client plants covering teaming agreements, prime/subcontract structures, joint ventures, SAM.gov readiness, and reading solicitations (14 hrs); teaming advisory for client plants (11 hrs); 33 hrs × $150/hr ≈ $5,000. [Confirm in KDM letter.]
B26: American Defense Alliance | C26: 6000 | D26: 6000 | E26: 6000 | F26: 6000 | G26: 6000 | H26: =SUM(C26,D26,E26,F26,G26) -> 30000 | I26: In-kind, $6,000/yr: mentor-protégé teaming lead. Council participation (8 hrs); matching client plants with defense primes and mentors under SBA and Department of War mentor-protégé programs, including a dedicated conference session (12 hrs); 20 hrs × $150/hr = $3,000, plus waived conference registrations for 6 students/clients (~$3,000 fair market value). [Confirm in ADA letter.]
B27: End-to-End Enterprise Solutions | C27: 5000 | D27: 5000 | E27: 5000 | F27: 5000 | G27: 5000 | H27: =SUM(C27,D27,E27,F27,G27) -> 25000 | I27: In-kind, $5,000/yr: CMMC readiness lead. Council participation (8 hrs); two CMMC readiness workshops for client plants covering Level 1 and Level 2 self-assessment, NIST SP 800-171, SPRS scoring, and DFARS 252.204-7012 (14 hrs incl. prep); CMMC gap-review clinics for client plants (11 hrs); 33 hrs × $150/hr ≈ $5,000. [Confirm in E2ES letter.]
B28: Let's Thryve | C28: 3500 | D28: 3500 | E28: 3500 | F28: 3500 | G28: 3500 | H28: =SUM(C28,D28,E28,F28,G28) -> 17500 | I28: In-kind, $3,500/yr: Council participation (8 hrs); coordination and delivery of two cybersecurity-awareness sessions for client plants and students (15 hrs); 23 hrs × $150/hr ≈ $3,500. [Confirm in Let's Thryve letter.]
B29: iHealth | C29: 1500 | D29: 1500 | E29: 1500 | F29: 1500 | G29: 1500 | H29: =SUM(C29,D29,E29,F29,G29) -> 7500 | I29: In-kind, $1,500/yr: Council participation (8 hrs) and one training session in its specialty (2 hrs); 10 hrs × $150/hr. [Role must be defined in its letter; if none, remove this row.]
B30: TOTAL (Cost Share) | C30: =SUM(C22:C29) -> 120750 | D30: =SUM(D22:D29) -> 120750 | E30: =SUM(E22:E29) -> 120750 | F30: =SUM(F22:F29) -> 120750 | G30: =SUM(G22:G29) -> 120750 | H30: =SUM(C30:G30) -> 603750 | I30: Total cost share $120,750/yr ($603,750 over five years) = 24.4% of total project cost; exceeds the 20% minimum. The SU MBDA LIFT Rural Business Center and SU Louisiana SBDC identify and prepare rural manufacturers but are not valued as cost share, because both are funded by other federal awards.

Sheet Subrecipients
B2: Project Title: | E2: Southern University Industrial Training and Assessment Center (SU ITAC)
B3: Applicant Name (Prime Recipient): | E3: Southern University and A&M College (Baton Rouge, LA) — UEI H7CJA7NX9WN3
B4: Application track (1 or 2): | E4: 1
A6: Subrecipients
B8: Subrecipient (if applicable) | C8: Budget Period 1 | D8: Budget Period 2 | E8: Budget Period 3 | F8: Budget Period 4 | G8: Budget Period 5 | H8: TOTAL | I8: Description/Explanation/Details (Please include any additional information necessary to clarify or otherwise enable reviewers to evaluate reasonableness of budget)
B9: Strategic Value Plus Solutions, LLC (V+) | C9: 100000 | D9: 100000 | E9: 100000 | F9: 100000 | G9: 100000 | H9: =SUM(C9:G9) -> 500000 | I9: Primary implementation partner: client pipeline from its network of 70+ veteran manufacturing SMEs; a field engineer on every site visit coaching students on productivity and plant operations (engineers appointed adjunct professors of practice); productivity, Lean, and supplier-readiness modules in the student boot camp; supplier readiness (quality, CMMC cybersecurity, operations, ITAR); implementation follow-up and Implementation Grant packets; incumbent-worker training. Includes V+ staff travel from Texas, Missouri, and Ohio: site visits grouped into two-plant trips (5 trips in BP1, 9 in BP2, 10/yr after), at ~$900 per drive trip (Texas) and ~$2,000 per flight trip (Missouri, Ohio), plus two boot-camp trips and incumbent-worker training trips; estimated travel $12,100 (BP1), $19,350 (BP2), $22,250 (BP3–5); labor and platform $87,900 (BP1) to $77,750 (BP3–5). 26.7% of federal share. Southern owns the training curriculum, energy-technical instruction, report sign-off, and certification; students perform all assessments.
H10: =SUM(C10:G10) -> 0
B11: Total Funds Requested | C11: =SUM(C9:C10) -> 100000 | D11: =SUM(D9:D10) -> 100000 | E11: =SUM(E9:E10) -> 100000 | F11: =SUM(F9:F10) -> 100000 | G11: =SUM(G9:G10) -> 100000 | H11: =SUM(C11:G11) -> 500000
